opentelemetry/sdk/extension/aws/version.py
opentelemetry/sdk/extension/aws/resource/__init__.py
opentelemetry/sdk/extension/aws/resource/_lambda.py
opentelemetry/sdk/extension/aws/resource/beanstalk.py
opentelemetry/sdk/extension/aws/resource/ec2.py
opentelemetry/sdk/extension/aws/resource/ecs.py
opentelemetry/sdk/extension/aws/resource/eks.py
opentelemetry/sdk/extension/aws/trace/__init__.py
opentelemetry/sdk/extension/aws/trace/aws_xray_id_generator.py
opentelemetry_sdk_extension_aws-2.0.1.dist-info/LICENSE
opentelemetry_sdk_extension_aws-2.0.1.dist-info/METADATA
opentelemetry_sdk_extension_aws-2.0.1.dist-info/WHEEL
opentelemetry_sdk_extension_aws-2.0.1.dist-info/entry_points.txt
opentelemetry_sdk_extension_aws-2.0.1.dist-info/top_level.txt
opentelemetry_sdk_extension_aws-2.0.1.dist-info/RECORD
