Metadata-Version: 2.1
Name: opentelemetry-sdk-extension-aws
Version: 2.0.1
Summary: AWS SDK extension for OpenTelemetry
Home-page: https://github.com/open-telemetry/opentelemetry-python-contrib/tree/main/sdk-extension/opentelemetry-sdk-extension-aws
Author: OpenTelemetry Authors
Author-email: cncf-opentelemetry-contributors@lists.cncf.io
License: Apache-2.0
Platform: any
Classifier: Development Status :: 5 - Production/Stable
Classifier: Intended Audience :: Developers
Classifier: License :: OSI Approved :: Apache Software License
Classifier: Programming Language :: Python
Classifier: Programming Language :: Python :: 3
Classifier: Programming Language :: Python :: 3.6
Classifier: Programming Language :: Python :: 3.7
Classifier: Programming Language :: Python :: 3.8
Classifier: Programming Language :: Python :: 3.9
Requires-Python: >=3.6
Provides-Extra: test
License-File: LICENSE
